brainweb_dl/__init__.py
brainweb_dl/_brainweb.py
brainweb_dl/_version.py
brainweb_dl/cli.py
brainweb_dl/mri.py
brainweb_dl/data/brainweb1_tissues.csv
brainweb_dl/data/brainweb20_tissues.csv
brainweb_dl-0.4.6.dist-info/licenses/LICENSE
brainweb_dl-0.4.6.dist-info/METADATA
brainweb_dl-0.4.6.dist-info/WHEEL
brainweb_dl-0.4.6.dist-info/entry_points.txt
brainweb_dl-0.4.6.dist-info/top_level.txt
brainweb_dl-0.4.6.dist-info/RECORD
