Metadata-Version: 2.4
Name: brainweb-dl
Version: 0.4.6
Summary: Download BrainWeb MRI data
Author-email: Pierre-Antoine Comby <pierre-antoine.comby@cea.fr>
License: MIT License
Project-URL: Homepage, https://github.com/paquiteau/brainweb-dl
Project-URL: Bug Reports, https://github.com/paquiteau/brainweb-dl/issues
Project-URL: Source, https://github.com/paquiteau/brainweb-dl
Keywords: brainweb,mri,download,data
Classifier: Development Status :: 3 - Alpha
Classifier: Intended Audience :: Developers
Classifier: License :: OSI Approved :: MIT License
Classifier: Programming Language :: Python :: 3.9
Classifier: Programming Language :: Python :: 3.10
Classifier: Programming Language :: Python :: 3.11
Classifier: Programming Language :: Python :: 3.12
Classifier: Programming Language :: Python :: 3.13
Requires-Python: >=3.9
License-File: LICENSE
Requires-Dist: requests
Requires-Dist: tqdm
Requires-Dist: numpy
Requires-Dist: scipy
Requires-Dist: nibabel
Requires-Dist: joblib
Provides-Extra: dev
Requires-Dist: black; extra == "dev"
Requires-Dist: isort; extra == "dev"
Provides-Extra: test
Requires-Dist: pytest; extra == "test"
Requires-Dist: pytest-black; extra == "test"
Requires-Dist: pytest-cov; extra == "test"
Requires-Dist: pytest-sugar; extra == "test"
Requires-Dist: pytest-xdist; extra == "test"
Provides-Extra: doc
Requires-Dist: sphinx; extra == "doc"
Requires-Dist: pydata-sphinx-theme; extra == "doc"
Requires-Dist: sphinx-gallery; extra == "doc"
Requires-Dist: matplotlib; extra == "doc"
Dynamic: license-file
